sketricgen/__init__.py
sketricgen/client.py
sketricgen/config.py
sketricgen/exceptions.py
sketricgen/py.typed
sketricgen/streaming.py
sketricgen/upload.py
sketricgen/models/__init__.py
sketricgen/models/requests.py
sketricgen/models/responses.py
sketricgen-0.1.1.dist-info/METADATA
sketricgen-0.1.1.dist-info/WHEEL
sketricgen-0.1.1.dist-info/RECORD
